taco/__init__.py
taco_infer-0.0.0.dist-info/METADATA
taco_infer-0.0.0.dist-info/WHEEL
taco_infer-0.0.0.dist-info/top_level.txt
taco_infer-0.0.0.dist-info/RECORD
