Metadata-Version: 2.1
Name: taco-infer
Version: 0.0.0
Summary: taco
Home-page: UNKNOWN
Author: huting
Author-email: suluner_2011@163.com
License: UNKNOWN
Platform: UNKNOWN
